<?xml version="1.0" encoding="UTF-8"?><record_update table="announcement">
    <announcement action="INSERT_OR_UPDATE">
        <active>true</active>
        <click_target>urlCurrent</click_target>
        <details/>
        <details_link_text>Check Now</details_link_text>
        <details_page/>
        <details_url>?id=kb_home</details_url>
        <dismiss_options>dismissible</dismiss_options>
        <display_first>true</display_first>
        <display_style display_value="La Jolla Urgent">7f8fe758c31023002ff2554d81d3ae99</display_style>
        <from>2022-10-06 11:57:40</from>
        <glyph>music</glyph>
        <glyph_alt_text/>
        <name>AnnouncementCroft</name>
        <public>true</public>
        <roles/>
        <show_for_unauthenticated_users_only>false</show_for_unauthenticated_users_only>
        <summary>Employees should communicate the concerns with your team</summary>
        <sys_class_name>announcement</sys_class_name>
        <sys_created_by>david.loo</sys_created_by>
        <sys_created_on>2022-10-06 14:29:26</sys_created_on>
        <sys_id>31f4f2ba1b525950d0c60fa9cc4bcb85</sys_id>
        <sys_name>AnnouncementCroft</sys_name>
        <sys_package display_value="Croft EC" source="x_833056_croft_ec">7155c17f97355110f769b4b3f153afb2</sys_package>
        <sys_policy/>
        <sys_scope display_value="Croft EC">7155c17f97355110f769b4b3f153afb2</sys_scope>
        <sys_update_name>announcement_31f4f2ba1b525950d0c60fa9cc4bcb85</sys_update_name>
        <title>Team Work </title>
        <to>2022-11-30 13:00:44</to>
        <type>67eaf134e7a3320075c2a117c2f6a9d2,52fa79f8e763320075c2a117c2f6a991</type>
    </announcement>
    <sys_translated_text action="delete_multiple" query="documentkey=31f4f2ba1b525950d0c60fa9cc4bcb85"/>
</record_update>
